{
  "version": 2,
  "name": "now-examples",
  "public": true,
  "builds": [
    {
      "src": "create-react-app/package.json",
      "use": "@now/static-build",
      "config": { "distDir": "build" }
    },
    {
      "src": "create-elm-app/package.json",
      "use": "@now/static-build",
      "config": { "distDir": "build" }
    },
    { "src": "docz/package.json", "use": "@now/static-build" },
    {
      "src": "gatsby/package.json",
      "use": "@now/static-build",
      "config": { "distDir": "public" }
    },
    { "src": "nextjs/package.json", "use": "@now/next" },

    {
      "src": "umijs/package.json",
      "use": "@now/static-build",
      "config": { "distDir": "dist" }
    },
    { "src": "vue/package.json", "use": "@now/static-build" }
  ]
}
